webappify/__init__.py
webappify-0.5.2.dist-info/METADATA
webappify-0.5.2.dist-info/WHEEL
webappify-0.5.2.dist-info/licenses/LICENSE
webappify-0.5.2.dist-info/RECORD
