Metadata-Version: 2.3
Name: WebAppify
Version: 0.5.2
Summary: Create desktop apps of your favourite websites
Project-URL: Homepage, https://git.snyman.info/raoul/webappify
Author-email: Raoul Snyman <raoul@snyman.info>
License-Expression: MIT
License-File: LICENSE
Keywords: Qt,Qt6,website
Classifier: Development Status :: 4 - Beta
Classifier: Environment :: MacOS X
Classifier: Environment :: Win32 (MS Windows)
Classifier: Environment :: X11 Applications
Classifier: Environment :: X11 Applications :: Qt
Classifier: Intended Audience :: Developers
Classifier: License :: OSI Approved :: MIT License
Classifier: Operating System :: OS Independent
Classifier: Programming Language :: Python :: 3
Classifier: Programming Language :: Python :: 3.10
Classifier: Programming Language :: Python :: 3.11
Classifier: Programming Language :: Python :: 3.12
Classifier: Topic :: Desktop Environment
Classifier: Topic :: Internet :: WWW/HTTP :: Browsers
Classifier: Topic :: Software Development :: Libraries :: Python Modules
Requires-Dist: pyside6
